flask_storm/__init__.py
flask_storm/_compat.py
flask_storm/debug.py
flask_storm/ext.py
flask_storm/sql.py
flask_storm/utils.py
Flask_Storm-1.0.0.dist-info/LICENSE
Flask_Storm-1.0.0.dist-info/METADATA
Flask_Storm-1.0.0.dist-info/WHEEL
Flask_Storm-1.0.0.dist-info/top_level.txt
Flask_Storm-1.0.0.dist-info/RECORD
