Metadata-Version: 2.1
Name: Flask-Storm
Version: 1.0.0
Summary: Storm integration for Flask.
Home-page: https://www.github.com/runfalk/flask-storm
Author: Andreas Runfalk
Author-email: andreas@runfalk.se
License: MIT
Platform: any
Classifier: Development Status :: 3 - Alpha
Classifier: Framework :: Flask
Classifier: Intended Audience :: Developers
Classifier: License :: OSI Approved :: MIT License
Classifier: Programming Language :: Python :: 2.7
Classifier: Programming Language :: Python :: 3.6
Classifier: Programming Language :: Python :: 3.7
Classifier: Programming Language :: Python :: 3.8
Classifier: Programming Language :: Python :: 3.9
Classifier: Topic :: Database
Classifier: Topic :: Utilities
Classifier: Topic :: Software Development :: Libraries
License-File: LICENSE
Requires-Dist: Flask
Provides-Extra: dev
Requires-Dist: flake8 ; extra == 'dev'
Requires-Dist: mock ; extra == 'dev'
Requires-Dist: pytest (>=3) ; extra == 'dev'
Requires-Dist: pytest-cov ; extra == 'dev'
Requires-Dist: pytest-helpers-namespace ; extra == 'dev'
Requires-Dist: sphinx ; extra == 'dev'
Requires-Dist: black ; (python_version >= "3.6") and extra == 'dev'
Provides-Extra: fancy
Requires-Dist: sqlparse (>=0.2.2) ; extra == 'fancy'
